brenthy_tools_beta/__init__.py
brenthy_tools_beta/__main__.py
brenthy_tools_beta/__project__.py
brenthy_tools_beta/brenthy_api.py
brenthy_tools_beta/brenthy_api_addresses.py
brenthy_tools_beta/bt_endpoints.py
brenthy_tools_beta/log.py
brenthy_tools_beta/requirements.txt
brenthy_tools_beta/utils.py
brenthy_tools_beta/version_utils.py
brenthy_tools_beta/versions.py
brenthy_tools_beta/brenthy_api_protocols/__init__.py
brenthy_tools_beta/brenthy_api_protocols/__main__.py
brenthy_tools_beta/brenthy_api_protocols/bap_3_brenthy_tools.py
brenthy_tools_beta/brenthy_api_protocols/bap_4_brenthy_tools.py
brenthy_tools_beta-4.0.11.dist-info/METADATA
brenthy_tools_beta-4.0.11.dist-info/WHEEL
brenthy_tools_beta-4.0.11.dist-info/top_level.txt
brenthy_tools_beta-4.0.11.dist-info/RECORD
