Metadata-Version: 2.4
Name: brenthy_tools_beta
Version: 4.0.11
Summary: A library for interacting with Brenthy (`brenthy_api`) and a collection of tools common to Brenthy Core and `brenthy_api`.
Author: Emendir
Project-URL: Homepage, https://github.com/emendir/BrenthyAndWalytis
Project-URL: Documentation, https://github.com/emendir/BrenthyAndWalytis/blob/master/Documentation/DocsOverview.md
Project-URL: Repository, https://github.com/emendir/BrenthyAndWalytis.git
Project-URL: IPFS, https://ipfs.io/ipns/k2k4r8nismm5mmgrox2fci816xvj4l4cudnuc55gkfoealjuiaexbsup/Projects/BrenthyAndWalytis
Requires-Dist: pyzmq
Requires-Dist: termcolor
Requires-Dist: pathspec
